{
	"chunks": [
		{
			"tags": "github api",
			"label": "clear git add",
			"content": "# git rm --staged .",
			"value": "1"
		},
		{
			"tags": "github api",
			"label": "docker what",
			"content": "sdcsdc dsfcdsfcdfc .",
			"value": "2"
		},
		{
			"tags": "github api",
			"label": "shell how",
			"content": "sdfcdf dfc df c dfc d fc dfc d fc dfc",
			"value": "3"
		},
		{
			"tags": "github api",
			"label": "which cool",
			"content": "dfcdfc dfkcdfc dkfcd fckjdbfc",
			"value": "4",
			"downloads": [
				{
					"label": "sampleconfig.js",
					"url": "https://example.com/file.pdf"
				}
			]
		},
		{
			"tags": "github api",
			"label": "andu kjdsfc dfsckbdfc",
			"content": "dlknxc sdckljnsdc sdknc sdkcjn",
			"value": "5"
		},
		{
			"tags": "github api",
			"label": "dsmc sdfcln fsdcln",
			"content": "dlknxc sdckljnsdc sdknc sdkcjn",
			"value": "6"
		},
		{
			"tags": "github api",
			"label": "jdb djbc dcjbdc",
			"content": "dlknxc sdckljnsdc sdknc sdkcjn",
			"value": "7"
		}
	]
}
